file_system_py/__init__.py
file_system_py-0.0.11.dist-info/METADATA
file_system_py-0.0.11.dist-info/WHEEL
file_system_py-0.0.11.dist-info/top_level.txt
file_system_py-0.0.11.dist-info/RECORD
