Metadata-Version: 2.1
Name: file_system_py
Version: 0.0.11
Summary: All-in-one file manipulation
Home-page: https://github.com/jeff-hykin/file-system-py
Author: Jeff Hykin
Author-email: jeff.hykin@gmail.com
License: MIT
Platform: UNKNOWN
Requires-Python: >=3.6
